dev_tools/__init__.py
dev_tools/clipboard_tools.py
dev_tools/dir_tools.py
dev_tools/file_tools.py
dev_tools/openai_tools.py
dev_tools/static_scraping.py
dev_tools/string_tools.py
devNexus-0.2.3.dist-info/LICENSE.txt
devNexus-0.2.3.dist-info/METADATA
devNexus-0.2.3.dist-info/WHEEL
devNexus-0.2.3.dist-info/top_level.txt
devNexus-0.2.3.dist-info/RECORD
