Metadata-Version: 2.1
Name: devNexus
Version: 0.2.3
Summary: A package containing dev tools to make development easier.
Home-page: https://github.com/2snufkin/developer_tools
Author: PZ
Author-email: rade.dvlp@gmail.com
Classifier: Programming Language :: Python :: 3
Classifier: License :: OSI Approved :: MIT License
Classifier: Operating System :: OS Independent
Requires-Python: >=3.7.1
License-File: LICENSE.txt
Requires-Dist: openai
Requires-Dist: pyperclip
Requires-Dist: requests
Requires-Dist: bs4
